wave_attenuation_1d/__init__.py
wave_attenuation_1d/cli.py
wave_attenuation_1d/solver.py
wave_attenuation_1d-0.1.5.dist-info/LICENSE
wave_attenuation_1d-0.1.5.dist-info/METADATA
wave_attenuation_1d-0.1.5.dist-info/WHEEL
wave_attenuation_1d-0.1.5.dist-info/entry_points.txt
wave_attenuation_1d-0.1.5.dist-info/RECORD
