Metadata-Version: 2.3
Name: wave-attenuation-1d
Version: 0.1.5
Summary: Simple 1D Wave Attenuation Model for Coastal Vegetation
License: MIT
Keywords: wave-attenuation,coastal-engineering,vegetation,numerical-modeling,shallow-water
Author: Sandy H. S. Herho
Author-email: sandy.herho@email.ucr.edu
Maintainer: Sandy H. S. Herho
Maintainer-email: sandy.herho@email.ucr.edu
Requires-Python: >=3.8,<3.13
Classifier: Development Status :: 4 - Beta
Classifier: Intended Audience :: Science/Research
Classifier: License :: OSI Approved :: MIT License
Classifier: Operating System :: OS Independent
Classifier: Programming Language :: Python :: 3
Classifier: Programming Language :: Python :: 3.8
Classifier: Programming Language :: Python :: 3.9
Classifier: Programming Language :: Python :: 3.10
Classifier: Programming Language :: Python :: 3.11
Classifier: Programming Language :: Python :: 3.12
Classifier: Topic :: Scientific/Engineering :: Atmospheric Science
Classifier: Topic :: Scientific/Engineering :: Physics
Requires-Dist: netcdf4 (>=1.5.0)
Requires-Dist: numba (>=0.54.0)
Requires-Dist: numpy (>=1.20.0)
Requires-Dist: tqdm (>=4.62.0)
Project-URL: Documentation, https://github.com/sandyherho/wave_attenuation_1d#readme
Project-URL: Homepage, https://github.com/sandyherho/wave_attenuation_1d
Project-URL: Repository, https://github.com/sandyherho/wave_attenuation_1d
